sealedsecretmgr/__init__.py
sealedsecretmgr/cli.py
sealedsecretmgr/sealedsecret.py
sealedsecretmgr-0.1.3.dist-info/METADATA
sealedsecretmgr-0.1.3.dist-info/entry_points.txt
sealedsecretmgr-0.1.3.dist-info/WHEEL
sealedsecretmgr-0.1.3.dist-info/LICENSE
sealedsecretmgr-0.1.3.dist-info/RECORD
