Metadata-Version: 2.1
Name: sealedsecretmgr
Version: 0.1.3
Summary: SealedSecret Manager
Home-page: https://github.com/dvincelli/sealedsecretmgr
License: Apache-2.0
Author: David Vincelli
Author-email: david.vincelli@gmail.com
Requires-Python: >=3.8,<4.0
Classifier: License :: OSI Approved :: Apache Software License
Classifier: Programming Language :: Python :: 3
Classifier: Programming Language :: Python :: 3.8
Classifier: Programming Language :: Python :: 3.9
Classifier: Programming Language :: Python :: 3.10
Classifier: Programming Language :: Python :: 3.11
Requires-Dist: black (>=22.12.0,<23.0.0)
Project-URL: Repository, https://github.com/dvincelli/sealedsecretmgr
